langutils/app/__init__.py
langutils/app/datetimeutils.py
langutils/app/dirutils.py
langutils/app/envvalues.py
langutils/app/fakerutils.py
langutils/app/fileutils.py
langutils/app/greputils.py
langutils/app/jsonutils.py
langutils/app/printutils.py
langutils/app/redisutils.py
langutils/app/stringutils.py
langutils/app/treeutils.py
langutils/app/usutils.py
langutils/app/utils.py
langutils/langs/__init__.py
langutils/langs/data/__init__.py
langutils/langs/data/fakesey/__init__.py
langutils/langs/data/fakesey/fakesey.py
yulibrary-0.0.2.dist-info/LICENSE
yulibrary-0.0.2.dist-info/METADATA
yulibrary-0.0.2.dist-info/WHEEL
yulibrary-0.0.2.dist-info/top_level.txt
yulibrary-0.0.2.dist-info/RECORD
